{
  "name": "Myrtie Howell",
  "age": 56,
  "address": {
    "street": "Awbod Court",
    "city": "Fihulisol",
    "state": "PA",
    "zip": "83894"
  },
  "contact": {
    "phone": "(344) 886-6527",
    "servicePhone": "800115119"
  },
  "birthday": "1988-09-02T04:32:30.463Z",
  "ip": "250.255.11.105",
  "foo": "bar",
  "profile": {
    "about": "Peh siswagu ivazif nuse oros pael onfon la en vi puwil ki bupikjob roz rujavgub nashoh. Basumu tovodfev timasrus dobbuvaro johifse su gore zugaf on wan tejzizise miv. Ewuzil alo cuvatla jobuvon uhu paskesuv kahbi de os nujzeru ege gewusi itopatpa kis telakcad up wohawte. Tunubbi tedcok lunegag fetha ugremu wez tagici opkum opra vothe comulo voz peri ocovooge. Oshek ala hotawna fu sasbegfah kagegu midubze kar imo toddusjar hak ko du hazaci vurhera tolib.",
    "bio": "Mijrif hep tethiczab at oloha fako su lakes hon vakzemov biw rekga fopeje zeeg. Hirdawe reltomzoz azobuc fegzi cuuma miroc hafeg icakimep zif casfuwi lekuvo gujiwevuj jabi vogueca iwguf. Nivos domfirud safurak mehewi powcoraji topomono li jozjepwom jihsa vudin nuaga li ko cis ra goge. Guhsatopo iva sifaz wu doc neowsi midazak du wawtog uzo vapdalsud onlelap li."
  },
  "apiKey": "64085490550d841ad5ee0ad785a9e2c6e25a7bcb42c94754b69c6eaa25f882bd",
  "currency": {
    "code": "GGP",
    "name": "Guernsey Pound"
  }
}